signatures/__init__.py
signatures/py.typed
signatures-0.3.1.dist-info/LICENSE
signatures-0.3.1.dist-info/WHEEL
signatures-0.3.1.dist-info/METADATA
signatures-0.3.1.dist-info/RECORD
