Metadata-Version: 2.1
Name: signatures
Version: 0.3.1
Summary: Utilities for inspecting and comparing Python function signatures.
Home-page: https://github.com/thehale/signatures
License: MPL-2.0
Keywords: introspection,signatures,functions,validation
Author: Joseph Hale
Author-email: me@jhale.dev
Requires-Python: >=3.8,<4.0
Classifier: License :: OSI Approved
Classifier: Programming Language :: Python :: 3
Classifier: Programming Language :: Python :: 3.10
Classifier: Programming Language :: Python :: 3.8
Classifier: Programming Language :: Python :: 3.9
Project-URL: Documentation, https://github.com/thehale/signatures
Project-URL: Repository, https://github.com/thehale/signatures
